rivista/__init__.py
rivista/version.py
rivista/compiler/atom.py
rivista/data/configs/activity.toml
rivista/data/configs/gemtext.toml
rivista/data/configs/mood.toml
rivista/data/configs/motd.toml
rivista/data/configs/settings.toml
rivista/data/graphics/ace.svg
rivista/data/graphics/agregore.svg
rivista/data/graphics/akregator.svg
rivista/data/graphics/alligator.svg
rivista/data/graphics/alpine.svg
rivista/data/graphics/alpine_linux.svg
rivista/data/graphics/angelfish.svg
rivista/data/graphics/antenna.svg
rivista/data/graphics/archlinux.svg
rivista/data/graphics/artix.svg
rivista/data/graphics/asf.svg
rivista/data/graphics/asteroidos.svg
rivista/data/graphics/beagle.svg
rivista/data/graphics/blasta.svg
rivista/data/graphics/buran.svg
rivista/data/graphics/capy.svg
rivista/data/graphics/castor.svg
rivista/data/graphics/cheogram.svg
rivista/data/graphics/commafeed.svg
rivista/data/graphics/conversations.svg
rivista/data/graphics/conversejs.svg
rivista/data/graphics/convo.svg
rivista/data/graphics/dahliaos.svg
rivista/data/graphics/debian.svg
rivista/data/graphics/deedum.svg
rivista/data/graphics/dergchat.svg
rivista/data/graphics/devuan.svg
rivista/data/graphics/dino.svg
rivista/data/graphics/ec.svg
rivista/data/graphics/emule.svg
rivista/data/graphics/eye.svg
rivista/data/graphics/falkon.svg
rivista/data/graphics/files.svg
rivista/data/graphics/freshrss.svg
rivista/data/graphics/g2dn.svg
rivista/data/graphics/gajim.svg
rivista/data/graphics/geminaut.svg
rivista/data/graphics/gemini.svg
rivista/data/graphics/gentoo.svg
rivista/data/graphics/geopard.svg
rivista/data/graphics/goodbytes.svg
rivista/data/graphics/gtk-gnutella.svg
rivista/data/graphics/html.svg
rivista/data/graphics/html5.svg
rivista/data/graphics/hyperbola.svg
rivista/data/graphics/i2p.svg
rivista/data/graphics/idiomdrottning.svg
rivista/data/graphics/kaidan.svg
rivista/data/graphics/kali.svg
rivista/data/graphics/kiss.svg
rivista/data/graphics/konqueror.svg
rivista/data/graphics/kristall.svg
rivista-2025.11.13.dist-info/METADATA
rivista-2025.11.13.dist-info/WHEEL
rivista-2025.11.13.dist-info/entry_points.txt
rivista-2025.11.13.dist-info/top_level.txt
rivista-2025.11.13.dist-info/RECORD
