Metadata-Version: 2.4
Name: Rivista
Version: 2025.11.13
Summary: A private journal publication and a content management system for XMPP
Author-email: Schimon Zachary <sch@fedora.email>
License: AGPL-3.0
Project-URL: Homepage, https://schapps.woodpeckersnest.eu/rivista/
Project-URL: Repository, https://git.xmpp-it.net/sch/Rivista
Project-URL: Issues, https://git.xmpp-it.net/sch/Rivista/issues
Keywords: atom,blog,cms,gemini,jabber,journal,news,opml,rss,sitemap,ssg,syndication,xml,xmpp
Platform: any
Classifier: Intended Audience :: End Users/Desktop
Classifier: License :: OSI Approved :: GNU Affero General Public License v3
Classifier: Natural Language :: English
Classifier: Programming Language :: Python
Classifier: Programming Language :: Python :: 3.10
Classifier: Topic :: Internet :: WWW/HTTP :: Dynamic Content :: News/Diary
Classifier: Topic :: Internet :: XMPP
Classifier: Topic :: Office/Business :: News/Diary
Requires-Dist: aiohttp
Requires-Dist: docutils
Requires-Dist: jetforce
Requires-Dist: lxml
Requires-Dist: pillow
Requires-Dist: python-dateutil
Requires-Dist: qrcode
Requires-Dist: rst2gemtext
Requires-Dist: slixmpp
Requires-Dist: tomli-w
